pd_multiprocessing/__init__.py
pd_multiprocessing/map.py
pd_multiprocessing/test/__init__.py
pd_multiprocessing/test/test_map_df_map.py
pd_multiprocessing-1.0.4.dist-info/LICENSE
pd_multiprocessing-1.0.4.dist-info/METADATA
pd_multiprocessing-1.0.4.dist-info/WHEEL
pd_multiprocessing-1.0.4.dist-info/top_level.txt
pd_multiprocessing-1.0.4.dist-info/RECORD
