Metadata-Version: 2.1
Name: pd-multiprocessing
Version: 1.0.4
Summary: pd_multiprocessing provides a simple, parallelized function to apply a user defined function rowwise on a Pandas Dataframe.
Home-page: https://github.com/stavrakidis/pd_multiprocessing
Author: Kyriakos Stavrakidis
License: MIT license
Project-URL: Source, https://github.com/stavrakidis/pd_multiprocessing
Project-URL: Tracker, https://github.com/stavrakidis/pd_multiprocessing/issues
Project-URL: Dokumentation, https://pd-multiprocessing.readthedocs.io/en/latest/
Platform: any
Classifier: Programming Language :: Python
Classifier: Programming Language :: Python :: 3
Classifier: Programming Language :: Python :: 3.4
Classifier: Programming Language :: Python :: 3.5
Classifier: Programming Language :: Python :: 3.6
Classifier: Programming Language :: Python :: 3.7
Requires-Python: >=3.4
Requires-Dist: pandas (>=0.22.0)
Requires-Dist: pytest (>=3.4.1)
